twirl/__init__.py
twirl/geometry.py
twirl/match.py
twirl/quads.py
twirl/triangles.py
twirl-0.4.2.dist-info/LICENSE
twirl-0.4.2.dist-info/METADATA
twirl-0.4.2.dist-info/WHEEL
twirl-0.4.2.dist-info/RECORD
