Metadata-Version: 2.1
Name: twirl
Version: 0.4.2
Summary: Astrometric plate solving in Python
Home-page: https://twirl.readthedocs.io
License: MIT
Keywords: astronomy,astrometry,plate-solving
Author: Lionel J. Garcia
Author-email: lionel_garcia@live.fr
Maintainer: Lionel J. Garcia
Maintainer-email: lionel_garcia@live.fr
Requires-Python: >=3.8,<4.0
Classifier: License :: OSI Approved :: MIT License
Classifier: Programming Language :: Python :: 3
Classifier: Programming Language :: Python :: 3.8
Classifier: Programming Language :: Python :: 3.9
Classifier: Programming Language :: Python :: 3.10
Classifier: Programming Language :: Python :: 3.11
Classifier: Programming Language :: Python :: 3.12
Provides-Extra: docs
Requires-Dist: astropy (>=5.1.1,<6.0.0)
Requires-Dist: astroquery (>=0.4.6,<0.5.0)
Requires-Dist: matplotlib (>=3.6.2,<4.0.0)
Requires-Dist: numpy (>=1.23.5,<2.0.0)
Requires-Dist: requests (>=2.28.1,<3.0.0)
Requires-Dist: scikit-image (>=0.21.0,<0.22.0)
Requires-Dist: scipy (>=1.9.3,<2.0.0)
Project-URL: Repository, https://github.com/lgrcia/twirl
